{
	"configurations" : 
	[
		{
			"directories" : 
			[
				{
					"build" : ".",
					"hasInstallRule" : true,
					"jsonFile" : "directory-.-beb2c20527fc68cef9ba.json",
					"minimumCMakeVersion" : 
					{
						"string" : "3.12"
					},
					"projectIndex" : 0,
					"source" : ".",
					"targetIndexes" : 
					[
						0,
						1
					]
				}
			],
			"name" : "",
			"projects" : 
			[
				{
					"directoryIndexes" : 
					[
						0
					],
					"name" : "Mini_Tarea_2",
					"targetIndexes" : 
					[
						0,
						1
					]
				}
			],
			"targets" : 
			[
				{
					"directoryIndex" : 0,
					"id" : "Mini_Tarea_2_uninstall::@6890427a1f51a3e7e1df",
					"jsonFile" : "target-Mini_Tarea_2_uninstall-b60fb1905036fbb20e24.json",
					"name" : "Mini_Tarea_2_uninstall",
					"projectIndex" : 0
				},
				{
					"directoryIndex" : 0,
					"id" : "uninstall::@6890427a1f51a3e7e1df",
					"jsonFile" : "target-uninstall-d4ffaba61741611daa92.json",
					"name" : "uninstall",
					"projectIndex" : 0
				}
			]
		}
	],
	"kind" : "codemodel",
	"paths" : 
	{
		"build" : "/home/maty/rob_movil_ws/src/build/Mini_Tarea_2",
		"source" : "/home/maty/rob_movil_ws/src/Mini_Tarea_2"
	},
	"version" : 
	{
		"major" : 2,
		"minor" : 3
	}
}
